aspy/__init__.py
aspy/refactor_imports/__init__.py
aspy/refactor_imports/classify.py
aspy/refactor_imports/import_obj.py
aspy/refactor_imports/sort.py
aspy.refactor_imports-3.0.2.dist-info/LICENSE
aspy.refactor_imports-3.0.2.dist-info/METADATA
aspy.refactor_imports-3.0.2.dist-info/WHEEL
aspy.refactor_imports-3.0.2.dist-info/top_level.txt
aspy.refactor_imports-3.0.2.dist-info/RECORD
