Metadata-Version: 2.1
Name: aspy.refactor-imports
Version: 3.0.2
Summary: Utilities for refactoring imports in python-like syntax.
Home-page: https://github.com/asottile/aspy.refactor_imports
Author: Anthony Sottile
Author-email: asottile@umich.edu
License: MIT
Platform: all
Classifier: License :: OSI Approved :: MIT License
Classifier: Programming Language :: Python :: 3
Classifier: Programming Language :: Python :: 3 :: Only
Classifier: Programming Language :: Python :: 3.7
Classifier: Programming Language :: Python :: 3.8
Classifier: Programming Language :: Python :: 3.9
Classifier: Programming Language :: Python :: 3.10
Classifier: Programming Language :: Python :: Implementation :: CPython
Classifier: Programming Language :: Python :: Implementation :: PyPy
Requires-Python: >=3.7
License-File: LICENSE
Requires-Dist: cached-property ; python_version < "3.8"
